<?xml version="1.0"?>
<ESBSubscriber xmlns:xsd="http://www.w3.org/2001/XMLSchema" xmlns:xsi="http://www.w3.org/2001/XMLSchema-instance">
  <Id>15b1d311-2926-48f7-b5f2-12e65ac797d8</Id>
  <Version>12a85262-25dd-45e5-895f-3170ff76578a</Version>
  <BusinessFlows />
  <Description />
  <Name>OrderPublisher</Name>
  <Group>General</Group>
  <IsSystemObject>false</IsSystemObject>
  <Bindings />
  <isAllowMultipleInstances>true</isAllowMultipleInstances>
  <UseUniqueWmiCounterName>true</UseUniqueWmiCounterName>
  <SubscriberId>OrderPublisher</SubscriberId>
  <ClientGroup>General</ClientGroup>
  <Zone>Enterprise</Zone>
  <Enabled>true</Enabled>
  <Anonymous>true</Anonymous>
  <Subscriptions>
    <Subscription>
      <TopicName>Orders.Processing</TopicName>
      <CanRead>false</CanRead>
      <CanWrite>true</CanWrite>
      <MatchMessagePatterns />
      <SubscriptionType>Topic</SubscriptionType>
    </Subscription>
  </Subscriptions>
  <MessagePipelines>
    <ClientPipelineItem>
      <Id>c74d8ac7-6b1b-4fe8-93d6-9a78f95a46e1</Id>
      <Version>15947428-729f-47fe-9555-9062d97e85ea</Version>
      <BusinessFlows />
      <Description />
      <Name>For Loop</Name>
      <IsSystemObject>false</IsSystemObject>
      <ApplyOnPublish>true</ApplyOnPublish>
      <ApplyOnReceive>false</ApplyOnReceive>
      <PipelineConditions>
        <Id>e0f0c49a-fefc-47b9-8025-fa8ea3ce3ffc</Id>
        <Version>1fd65005-a728-4691-9cb6-3956558ea2e1</Version>
        <BusinessFlows />
        <Description />
        <IsSystemObject>false</IsSystemObject>
        <Condition />
      </PipelineConditions>
    </ClientPipelineItem>
  </MessagePipelines>
  <AllowMultipleInstances>true</AllowMultipleInstances>
  <LogActivity>false</LogActivity>
  <LogFile />
  <LogSession>true</LogSession>
</ESBSubscriber>