<?xml version="1.0"?>
<ESBSubscriber xmlns:xsd="http://www.w3.org/2001/XMLSchema" xmlns:xsi="http://www.w3.org/2001/XMLSchema-instance">
  <Id>a019f0d3-0140-4641-a4ae-e354c729fa62</Id>
  <Version>6be7735e-bf10-4a73-9560-e12bf6bd6d55</Version>
  <BusinessFlows />
  <Description />
  <Name>OrdersSubscriber</Name>
  <Group>General</Group>
  <IsSystemObject>false</IsSystemObject>
  <IsPrivate>false</IsPrivate>
  <Bindings />
  <SubscriberId>OrdersSubscriber</SubscriberId>
  <ClientGroup>General</ClientGroup>
  <Zone>Enterprise</Zone>
  <Enabled>true</Enabled>
  <Subscriptions>
    <Subscription>
      <TopicName>Fulfillment.Request</TopicName>
      <CanRead>false</CanRead>
      <CanWrite>true</CanWrite>
      <SubscriptionType>Topic</SubscriptionType>
    </Subscription>
    <Subscription>
      <TopicName>Orders.Request</TopicName>
      <CanRead>true</CanRead>
      <CanWrite>false</CanWrite>
      <SubscriptionType>Topic</SubscriptionType>
    </Subscription>
    <Subscription>
      <TopicName>Orders.Response</TopicName>
      <CanRead>false</CanRead>
      <CanWrite>true</CanWrite>
      <SubscriptionType>Topic</SubscriptionType>
    </Subscription>
  </Subscriptions>
  <ACL />
  <Anonymous>true</Anonymous>
  <AllowMultipleInstances>true</AllowMultipleInstances>
  <LogActivity>false</LogActivity>
  <UseUniqueWmiCounterName>false</UseUniqueWmiCounterName>
</ESBSubscriber>