<?xml version="1.0"?>
<ESBServicePolicy xmlns:xsd="http://www.w3.org/2001/XMLSchema" xmlns:xsi="http://www.w3.org/2001/XMLSchema-instance">
  <Id>afd46bc0-9eda-469c-b39b-f4c76c7bff03</Id>
  <Version>2379c8cf-a902-431f-93e0-42bd0a1f354b</Version>
  <Name>Default</Name>
  <Description>Default service policy</Description>
  <Group>General</Group>
  <IsSystemObject>false</IsSystemObject>
  <RequestReplyTimeout>60</RequestReplyTimeout>
  <RetryCount>1</RetryCount>
  <RetryInterval>1</RetryInterval>
  <OnErrorAuditToDatabase>false</OnErrorAuditToDatabase>
  <OnErrorAuditToFile>false</OnErrorAuditToFile>
  <OnErrorRepublishMessage>false</OnErrorRepublishMessage>
  <OnErrorRollback>false</OnErrorRollback>
  <RepublishTopic />
  <AlwaysAvailable>true</AlwaysAvailable>
  <InlcudeAsExceptions>false</InlcudeAsExceptions>
  <StartAndStopAdapterAccordingToAvailability>true</StartAndStopAdapterAccordingToAvailability>
  <HttpStatusCodes />
  <DoNotApplyPolicyIfFaultContract>false</DoNotApplyPolicyIfFaultContract>
  <RollbackMessageExpirationSeconds>300</RollbackMessageExpirationSeconds>
  <RollbackDelaySeconds>60</RollbackDelaySeconds>
</ESBServicePolicy>