<?xml version="1.0"?>
<ESBSubscriber xmlns:xsd="http://www.w3.org/2001/XMLSchema" xmlns:xsi="http://www.w3.org/2001/XMLSchema-instance">
  <Id>092d78e9-4a09-4f6a-af09-5da90a51cc14</Id>
  <Version>8fe2bb19-f1a0-4de4-95f5-9955e82d7449</Version>
  <Name>InquiryResponder</Name>
  <Description />
  <Group>General</Group>
  <IsSystemObject>false</IsSystemObject>
  <AllowMultipleInstances>true</AllowMultipleInstances>
  <UseUniqueWmiCounterName>true</UseUniqueWmiCounterName>
  <SubscriberId>InquiryResponder</SubscriberId>
  <ClientGroup>General</ClientGroup>
  <Zone>Enterprise</Zone>
  <Enabled>true</Enabled>
  <Anonymous>true</Anonymous>
  <Subscriptions>
    <Subscription>
      <TopicName>Inquiries</TopicName>
      <CanRead>true</CanRead>
      <CanWrite>false</CanWrite>
      <SubscriptionType>Topic</SubscriptionType>
    </Subscription>
  </Subscriptions>
  <LogActivity>false</LogActivity>
  <LogFile />
  <LogSession>true</LogSession>
</ESBSubscriber>